instapull/__init__.py
instapull/__main__.py
instapull/classes.py
instapull/downloader.py
instapull/exceptions.py
tests/__init__.py
tests/mock_requests.py
tests/mock_util.py
tests/test_download.py
tests/test_download_internals.py
instapull-1.0.dist-info/LICENSE
instapull-1.0.dist-info/METADATA
instapull-1.0.dist-info/WHEEL
instapull-1.0.dist-info/entry_points.txt
instapull-1.0.dist-info/top_level.txt
instapull-1.0.dist-info/RECORD
