Metadata-Version: 2.1
Name: instapull
Version: 1.0
Summary: Simple tool that lets you dump Instagram posts by user or hashtag
Home-page: https://www.frodehus.com
Author: Frode Hus
Author-email: frode.hus@outlook.com
License: UNKNOWN
Platform: UNKNOWN
Classifier: Programming Language :: Python :: 3
Classifier: License :: OSI Approved :: MIT License
Requires-Python: >=3.6
Requires-Dist: requests
Requires-Dist: argparse
Requires-Dist: alive-progress
